[{"vehicle_type":"Ciezarowe","brand":"sterling","model":"AT","generation":"EPA2001","engine":"9500 14.6 V6 476 KM 350 kW","url":"/katalog-mocy/sterling/at/epa2001/9500-14-6-v6-476-km-350-kw","stages":[{"stage_label":"Eko Tuning","stage_name":"Eko tuning | Stage eko","orig_hp":476,"orig_nm":2244,"chip_hp":487,"chip_nm":2296,"gain_hp":11,"gain_nm":52},{"stage_label":"Chip Tuning","stage_name":"Chip tuning | Stage 1 / Standard","orig_hp":476,"orig_nm":2244,"chip_hp":509,"chip_nm":2400,"gain_hp":33,"gain_nm":156},{"stage_label":"Extreme Tuning","stage_name":"Extreme tuning | Stage 2 / Stage 3","orig_hp":476,"orig_nm":2244,"chip_hp":null,"chip_nm":null,"gain_hp":null,"gain_nm":null}]},{"vehicle_type":"Ciezarowe","brand":"sterling","model":"AT","generation":"EPA2007","engine":"9500 12.7 V6 380 KM 279 kW","url":"/katalog-mocy/sterling/at/epa2007/9500-12-7-v6-380-km-279-kw","stages":[{"stage_label":"Eko Tuning","stage_name":"Eko tuning | Stage eko","orig_hp":380,"orig_nm":1830,"chip_hp":389,"chip_nm":1873,"gain_hp":9,"gain_nm":43},{"stage_label":"Chip Tuning","stage_name":"Chip tuning | Stage 1 / Standard","orig_hp":380,"orig_nm":1830,"chip_hp":407,"chip_nm":1959,"gain_hp":27,"gain_nm":129},{"stage_label":"Extreme Tuning","stage_name":"Extreme tuning | Stage 2 / Stage 3","orig_hp":380,"orig_nm":1830,"chip_hp":null,"chip_nm":null,"gain_hp":null,"gain_nm":null}]},{"vehicle_type":"Ciezarowe","brand":"sterling","model":"AT","generation":"EPA2007","engine":"9500 12.5 V6 431 KM 317 kW","url":"/katalog-mocy/sterling/at/epa2007/9500-12-5-v6-431-km-317-kw","stages":[{"stage_label":"Eko Tuning","stage_name":"Eko tuning | Stage eko","orig_hp":431,"orig_nm":2102,"chip_hp":441,"chip_nm":2151,"gain_hp":10,"gain_nm":49},{"stage_label":"Chip Tuning","stage_name":"Chip tuning | Stage 1 / Standard","orig_hp":431,"orig_nm":2102,"chip_hp":461,"chip_nm":2249,"gain_hp":30,"gain_nm":147},{"stage_label":"Extreme Tuning","stage_name":"Extreme tuning | Stage 2 / Stage 3","orig_hp":431,"orig_nm":2102,"chip_hp":null,"chip_nm":null,"gain_hp":null,"gain_nm":null}]},{"vehicle_type":"Ciezarowe","brand":"sterling","model":"AT","generation":"EPA2007","engine":"9500 12.8 V6 451 KM 332 kW","url":"/katalog-mocy/sterling/at/epa2007/9500-12-8-v6-451-km-332-kw","stages":[{"stage_label":"Eko Tuning","stage_name":"Eko tuning | Stage eko","orig_hp":451,"orig_nm":2237,"chip_hp":462,"chip_nm":2289,"gain_hp":11,"gain_nm":52},{"stage_label":"Chip Tuning","stage_name":"Chip tuning | Stage 1 / Standard","orig_hp":451,"orig_nm":2237,"chip_hp":483,"chip_nm":2394,"gain_hp":32,"gain_nm":157},{"stage_label":"Extreme Tuning","stage_name":"Extreme tuning | Stage 2 / Stage 3","orig_hp":451,"orig_nm":2237,"chip_hp":null,"chip_nm":null,"gain_hp":null,"gain_nm":null}]}]